{
  "awakening_region": "Bronzepaw Hamlet, Obsidia",
  "level": 3,
  "name": "Theron Oakheart",
  "rarity": "Rare",
  "classes": ["Ranger", "Herbalist", "Lorekeeper"],
  "race": "Bearkin",
  "age": 35,
  "items_held": [
    "Custom Longbow",
    "Herbal Pouch",
    "Lore Scrolls",
    "Magical Lenses",
    "Healing Salves"
  ],
  "character_backstory": "A bearkin from Bronzepaw Hamlet, known for his intellectual pursuits and his connection to nature.",
  "personal_ambitions_goals": "To maintain the balance between his community and the natural world, sharing knowledge and wisdom.",
  "irl_backstory": "AI-Controlled Character",
  "memories": "Born and raised in the virtual world of Evergreen, with deep roots in his community.",
  "gender": "Male",
  "appearance": {
    "eye_color": "Brown",
    "fur_color": "Medium Brown",
    "skin_tone": "Not Applicable",
    "physical_size": "Slightly above average height",
    "physical_build": "Lean and agile",
    "notable_characteristics": "Relaxed demeanor, distinctive magical lenses"
  },
  "notable_affinities": {
    "religions": ["Nature Worship"],
    "cultures": ["Bearkin"],
    "guild_membership": "None",
    "reputations": []
  },
  "special_abilities": [
    "Expert Tracker",
    "Nature's Insight",
    "Herbal Mastery",
    "Spiritual Resilience",
    "Enhanced Bear Senses"
  ],
  "base_combat_statistics": {
    "health_points": 4,
    "attack": 4,
    "defense": 3,
    "speed": 5,
    "magic_defense": 4
  },
  "noncombat_statistics": {
    "big_5_personality_traits": {
      "openness": 75,
      "conscientiousness": 85,
      "extraversion": 55,
      "agreeableness": 70,
      "neuroticism": 30
    },
    "charisma": 60,
    "intelligence": 80,
    "dexterity": 65,
    "strength": 60
  },
  "current_state": {
    "health_status": "Full Health",
    "ailments_effects": "None",
    "hunger_status": "Satiated",
    "fatigue_status": "Rested"
  }
}
